setup.py
mailplate/__init__.py
mailplate/mailplate.py
mailplate.egg-info/PKG-INFO
mailplate.egg-info/SOURCES.txt
mailplate.egg-info/dependency_links.txt
mailplate.egg-info/top_level.txt
mailplate/driver/mailgun.py
mailplate/driver/ses.py
mailplate/driver/smtp.py
mailplate/driver/smtps.py