Metadata-Version: 1.1
Name: mailplate
Version: 0.601
Summary: Send Muli-Language Multi-Transport Template-Driven Email
Home-page: https://github.com/avnr/mailplate
Author: Avner Herskovits
Author-email: avnr_ at outlook.com
License: UNKNOWN
Download-URL: https://github.com/avnr/mailplate/tarball/0.601
Platform: UNKNOWN
Classifier: Development Status :: 4 - Beta
Classifier: Environment :: Console
Classifier: Environment :: No Input/Output (Daemon)
Classifier: Environment :: Other Environment
Classifier: Intended Audience :: Developers
Classifier: Intended Audience :: Information Technology
Classifier: Intended Audience :: System Administrators
Classifier: License :: OSI Approved :: MIT License
Classifier: Operating System :: OS Independent
Classifier: Programming Language :: Python
Classifier: Topic :: Communications :: Email
Classifier: Topic :: Utilities
